src/__init__.py
src/cli.py
src/pld.py
src/report.py
pdf_language_detector-0.0.11.dist-info/METADATA
pdf_language_detector-0.0.11.dist-info/entry_points.txt
pdf_language_detector-0.0.11.dist-info/WHEEL
pdf_language_detector-0.0.11.dist-info/RECORD
