Metadata-Version: 2.1
Name: pdf-language-detector
Version: 0.0.11
Summary: A python script to iterate over a list of PDF in a directory and try to guess their language with Tesseract OCR.
Author: ICIJ
Author-email: engineering@icij.org
Requires-Python: >=3.8.1,<4.0.0
Classifier: Programming Language :: Python :: 3
Classifier: Programming Language :: Python :: 3.9
Classifier: Programming Language :: Python :: 3.10
Classifier: Programming Language :: Python :: 3.11
Requires-Dist: langcodes[data] (>=3.3.0,<4.0.0)
Requires-Dist: lingua-language-detector (>=1.3.2,<2.0.0)
Requires-Dist: pytesseract (>=0.3.10,<0.4.0)
Requires-Dist: rich (>=13.4.2,<14.0.0)
Requires-Dist: sh (>=2.0.4,<3.0.0)
Requires-Dist: spytula (==0.0.3)
Requires-Dist: typer[all] (>=0.9.0,<0.10.0)
